pypolsar/__init__.py
pypolsar/__main__.py
pypolsar/example.py
pypolsar/filters/__init__.py
pypolsar/filters/spatial.py
pypolsar/geo/__init__.py
pypolsar/geo/geo.py
pypolsar/io/__init__.py
pypolsar/io/project/__init__.py
pypolsar/io/project/project.py
pypolsar/io/rat/__init__.py
pypolsar/io/rat/geo_rat.py
pypolsar/io/rat/ste_io.py
pypolsar/misc/__init__.py
pypolsar/opertaions/__init__.py
pypolsar/opertaions/operation.py
pypolsar/plot/__init__.py
pypolsar/plot/dem.py
pypolsar/plot/map.py
pypolsar/plot/permasar.py
pypolsar/polsar/__init__.py
pypolsar/polsar/calibration/__init__.py
pypolsar/polsar/classification/__init__.py
pypolsar/polsar/decomposition/__init__.py
pypolsar/polsar/decomposition/eigen.py
pypolsar/polsar/decomposition/operators.py
pypolsar/polsar/filters/__init__.py
pypolsar/polsar/filters/additive_noise.py
pypolsar/polsar/parameters/__init__.py
pypolsar/polsar/parameters/ent_ans_alpha.py
pypolsar/polsar/parameters/ratios.py
pypolsar/polsar/processor.py
pypolsar/py.typed
pypolsar/stats/__init__.py
pypolsar/stats/timer.py
pypolsar/utils/__init__.py
pypolsar/utils/plot.py
pypolsar/utils/plot_polsar.py
pypolsar-2.1.0.dist-info/entry_points.txt
pypolsar-2.1.0.dist-info/LICENSE
pypolsar-2.1.0.dist-info/WHEEL
pypolsar-2.1.0.dist-info/METADATA
pypolsar-2.1.0.dist-info/RECORD
