Metadata-Version: 2.1
Name: pypolsar
Version: 2.1.0
Summary: PyPolSAR is a python module for Polarimetric Synthetic Aperture Radar (PolSAR) data processing.
Home-page: https://github.com/IslamAlam/pypolsar
License: GPL-3.0-or-later
Keywords: pypolsar,gdal,numpy,xarray
Author: Earth-Observation
Author-email: is3mansour@gmail.com
Requires-Python: >=3.7,<4.0
Classifier: Development Status :: 3 - Alpha
Classifier: Intended Audience :: Developers
Classifier: License :: OSI Approved :: GNU General Public License v3 or later (GPLv3+)
Classifier: Operating System :: OS Independent
Classifier: Programming Language :: Python :: 3
Classifier: Programming Language :: Python :: 3.3
Classifier: Programming Language :: Python :: 3.4
Classifier: Programming Language :: Python :: 3.5
Classifier: Programming Language :: Python :: 3.6
Classifier: Programming Language :: Python :: 3.7
Classifier: Programming Language :: Python :: 3.8
Classifier: Programming Language :: Python :: 3.9
Classifier: Topic :: Software Development :: Libraries :: Python Modules
Requires-Dist: cython (>=0.29.21,<0.30.0)
Requires-Dist: h5py (>=2.10.0,<3.0.0)
Requires-Dist: importlib_metadata (>=1.6.0,<2.0.0); python_version < "3.8"
Requires-Dist: mako (>=1.1.3,<2.0.0)
Requires-Dist: matplotlib (>=3.3.2,<4.0.0)
Requires-Dist: numba (>=0.51.2,<0.52.0)
Requires-Dist: numpy (>=1.19.2,<2.0.0)
Requires-Dist: pillow (>=7.2.0,<8.0.0)
Requires-Dist: pre-commit (>=2.5.1,<3.0.0)
Requires-Dist: readline (>=6.2.4,<7.0.0)
Requires-Dist: rich (>=2.2.2,<3.0.0)
Requires-Dist: scikit-image (>=0.17.2,<0.18.0)
Requires-Dist: scipy (>=1.5.2,<2.0.0)
Requires-Dist: seaborn (>=0.11.0,<0.12.0)
Requires-Dist: typer[all] (>=0.2.1,<0.3.0)
Requires-Dist: xarray (>=0.16.0,<0.17.0)
Project-URL: Repository, https://github.com/IslamAlam/pypolsar
